zodchy_inbox/__init__.py
zodchy_inbox/contracts.py
zodchy_inbox/handlers.py
zodchy_inbox-0.1.1.dist-info/METADATA
zodchy_inbox-0.1.1.dist-info/WHEEL
zodchy_inbox-0.1.1.dist-info/RECORD
