Metadata-Version: 2.1
Name: zodchy-inbox
Version: 0.1.1
Summary: Inbox pattern for zodchy architecture
Home-page: https://github.com/smairon/zodchy-inbox
Author: Smairon
Author-email: man@smairon.ru
Requires-Python: >=3.11,<4.0
Classifier: Programming Language :: Python :: 3
Classifier: Programming Language :: Python :: 3.11
Classifier: Programming Language :: Python :: 3.12
Requires-Dist: pydantic (>=2,<3)
Requires-Dist: zodchy (>=0,<1)
Project-URL: Repository, https://github.com/smairon/zodchy-inbox
